coretypes/__init__.py
coretypes/__version__.py
coretypes/errors/__init__.py
coretypes/errors/trade/__init__.py
coretypes/errors/trade/base.py
coretypes/errors/trade/client.py
coretypes/errors/trade/entrust.py
coretypes/errors/trade/server.py
coretypes/quote_fetcher.py
coretypes/types.py
zillionare_core_types-0.6.3.dist-info/LICENSE
zillionare_core_types-0.6.3.dist-info/METADATA
zillionare_core_types-0.6.3.dist-info/WHEEL
zillionare_core_types-0.6.3.dist-info/RECORD
